denest/__about__.py
denest/__init__.py
denest/__main__.py
denest/base_object.py
denest/parameters.py
denest/session.py
denest/simulation.py
denest/io/__init__.py
denest/io/load.py
denest/io/save.py
denest/network/__init__.py
denest/network/layers.py
denest/network/models.py
denest/network/projections.py
denest/network/recorders.py
denest/network/utils.py
denest/utils/__init__.py
denest/utils/autodict.py
denest/utils/misc.py
denest/utils/validation.py
denest-1.0.1.dist-info/LICENSE
denest-1.0.1.dist-info/METADATA
denest-1.0.1.dist-info/WHEEL
denest-1.0.1.dist-info/top_level.txt
denest-1.0.1.dist-info/RECORD
