Metadata-Version: 2.1
Name: denest
Version: 1.0.1
Summary: A declarative interface for specifying and running simulations in NEST.
Home-page: http://github.com/tombugnon/denest
Author: Tom Bugnon and William G. P. Mayner
Author-email: tombugnon@hotmail.com
License: GNU General Public License v3.0
Project-URL: Bug Reports, https://github.com/tombugnon/denest/issues
Project-URL: Documentation, https://denest.readthedocs.io
Platform: UNKNOWN
Classifier: Development Status :: 3 - Alpha
Classifier: Intended Audience :: Developers
Classifier: Natural Language :: English
Classifier: Programming Language :: Python
Classifier: Programming Language :: Python :: 3.6
Classifier: Programming Language :: Python :: 3.7
Classifier: Programming Language :: Python :: 3.8
Classifier: Topic :: Scientific/Engineering
Requires-Dist: docopt
Requires-Dist: numpy
Requires-Dist: pandas
Requires-Dist: pyyaml
Requires-Dist: tqdm
